limitlessled/__init__.py
limitlessled/bridge.py
limitlessled/group/__init__.py
limitlessled/group/commands/__init__.py
limitlessled/group/commands/legacy.py
limitlessled/group/commands/v6.py
limitlessled/group/dimmer.py
limitlessled/group/rgbcct.py
limitlessled/group/rgbw.py
limitlessled/group/rgbww.py
limitlessled/group/white.py
limitlessled/group/wrgb.py
limitlessled/pipeline.py
limitlessled/presets.py
limitlessled/util.py
limitlessled8z-1.2.0.dist-info/LICENSE
limitlessled8z-1.2.0.dist-info/METADATA
limitlessled8z-1.2.0.dist-info/WHEEL
limitlessled8z-1.2.0.dist-info/RECORD
