Metadata-Version: 2.3
Name: limitlessled8z
Version: 1.2.0
Summary: Control LimitlessLED, Milight, etc. products.
License: MIT
Author: happyleaves
Author-email: happyleaves.tfr@gmail.com
Requires-Python: >=3.9,<4.0
Classifier: License :: OSI Approved :: MIT License
Classifier: Operating System :: OS Independent
Classifier: Programming Language :: Python :: 3
Classifier: Programming Language :: Python :: 3.9
Classifier: Programming Language :: Python :: 3.10
Classifier: Programming Language :: Python :: 3.11
Classifier: Programming Language :: Python :: 3.12
Classifier: Programming Language :: Python :: 3.13
Project-URL: Repository, https://github.com/jbchouinard/python-limitlessled8z/
